{"type":"FeatureCollection","features":[{"type":"Feature","geometry":{"type":"Point","coordinates":[134.052159,34.391237]},"properties":{"#property":"1","name":"高松市国民健康保険女木診療所","nickname":"オーテがみまもるクリニック","address":"高松市女木町112","telephoneNumber":"087-873-0103","referenceObject":"https://takamatsu-udmap.jp/ud/2019021803543/","note":"","availableDate":"月火木金","startTime":"月・木：14:00、火・金：10:30","endTime":"月・木：17:00、火・金：12:00","availableDateNote":"土日祝・振替休日・年末・年始（12月29日～1月3日）利用不可"}},{"type":"Feature","geometry":{"type":"Point","coordinates":[134.0542368597885,34.42261717064336]},"properties":{"#property":"2","name":"高松市国民健康保険男木診療所","nickname":"SETOLAS　男木島診療所","address":"高松市男木町1988","telephoneNumber":"087-873-0003","referenceObject":"https://takamatsu-udmap.jp/ud/2019030500044/","note":"","availableDate":"月火木金","startTime":"月・木：10:45、火・金：14:00","endTime":"月・木：12:00、火・金：16:45","availableDateNote":"土日祝・振替休日・年末・年始（12月29日～1月3日）利用不可"}}]}