{"type":"FeatureCollection","features":[{"type":"Feature","geometry":{"type":"Point","coordinates":[134.08198167,34.17037417]},"properties":{"#property":"1","name":"塩江湯愛の郷センター（道の駅しおのえ）","address":"高松市塩江町安原上東390-4","telephoneNumber":"893-1378","referenceObject":"https://www.takamatsu-kankou.net/spot/detail/347","note":"","availableDate":"月水木金土日","startTime":"08:00","endTime":"19:00","availableDateNote":"定休日：火曜日（祝日の場合は翌日）　　　　　12月31日～1月2日営業時間：１１月～２月は午前８時～午後６時","basicPrice":"無料","detailPrice":"","description":"国道１９３号の香東川上流の川沿いに位置し、塩江温泉郷の目印になっている。「観光物産センターしおのえ」が隣接していて、塩江の特産品が購入できる。","access":"JR高松駅からバスで約７５分。","parkingInformation":"駐車スペース２５台"}},{"type":"Feature","geometry":{"type":"Point","coordinates":[134.00727306,34.23944611]},"properties":{"#property":"2","name":"香南楽湯","address":"高松市香南町横井997-2","telephoneNumber":"815-8585","referenceObject":"http://www.souyu.co.jp/kounan/","note":"","availableDate":"月火水木金土日","startTime":"10:00","endTime":"23:00","availableDateNote":"定休日：第３水曜日（祝日の場合は翌日）","basicPrice":"大人　670円小人（小学生）310円高齢者（65歳以上）510円","detailPrice":"","description":"木漏れ日のある「陽の風呂」と御影石・庵治石の「石の風呂」の天然温泉があるユニークな道の駅。館内には、おみやげショップの他に、レストラン、軽食コーナー、ボディケアがあり、産直市「香南朝市」も併設。","access":"JR高松駅からバスで約４５分。","parkingInformation":"駐車スペース１０１台"}},{"type":"Feature","geometry":{"type":"Point","coordinates":[134.15671167,34.33351]},"properties":{"#property":"3","name":"高松市道の駅源平の里むれ","address":"高松市牟礼町原631-7","telephoneNumber":"845-6080","referenceObject":"http://www.genpei-mure.com/","note":"","availableDate":"月火水木金土日","startTime":"09:00","endTime":"17:00","availableDateNote":"定休日：第1、第3水曜日（祝日の場合は翌平日）","basicPrice":"無料","detailPrice":"","description":"国道11号線にある道の駅。地元の特産品等の物販施設や食事処のほかにお遍路さんのための休憩施設、駐車場、トイレ、情報ステーションも併設。","access":"琴電房前駅より徒歩10分。志度ICから10分。","parkingInformation":"大型13台、普通車47台、身障者用2台"}}]}