{"type":"FeatureCollection","features":[{"type":"Feature","geometry":{"type":"Point","coordinates":[134.12144972,34.36830806]},"properties":{"#property":"1","name":"高松市深間ふれあいセンター","address":"高松市庵治町6391-17","telephoneNumber":"","referenceObject":"","note":"","availableDate":"月火水木金土日","startTime":"09:00","endTime":"22:00","availableDateNote":"国民の祝日に関する法律に規定する休日及び年末年始（12月29日から翌年の1月3日まで）は利用不可。"}},{"type":"Feature","geometry":{"type":"Point","coordinates":[134.07372833,34.12608194]},"properties":{"#property":"2","name":"高松市西山ふれあいセンター","address":"高松市塩江町上西甲947-3","telephoneNumber":"087-893-0192","referenceObject":"","note":"","availableDate":"月火水木金土日","startTime":"09:00","endTime":"21:00","availableDateNote":"国民の祝日に関する法律に規定する休日及び年末年始（12月29日から翌年の1月3日まで）は利用不可。"}}]}