{"type":"FeatureCollection","features":[{"type":"Feature","geometry":{"type":"Point","coordinates":[134.0148103,34.2623891]},"properties":{"#property":"1","name":"高松市西部クリーンセンター","address":"高松市川部町930-1","telephoneNumber":"087-885-2727","referenceObject":"http://www.city.takamatsu.kagawa.jp/kurashi/shinotorikumi/soshikihyo/seibu_clean.html","note":"","availableDate":"月火水木金土","startTime":"08:30","endTime":"16:30","availableDateNote":"利用可能曜日は祝祭日及び年末年始を除く。破砕ごみの搬入受付は15：00まで。ただし、土曜日は12：00まで。なお、破砕ごみの一般持込みは土曜日のみ。"}},{"type":"Feature","geometry":{"type":"Point","coordinates":[134.03223,34.19943]},"properties":{"#property":"2","name":"高松市南部クリーンセンター","address":"高松市塩江町安原下第3号2084-1","telephoneNumber":"087-890-2190","referenceObject":"http://www.city.takamatsu.kagawa.jp/kurashi/shinotorikumi/soshikihyo/nanbu_clean.html","note":"","availableDate":"月火水木金","startTime":"08:30","endTime":"16:30","availableDateNote":"利用可能曜日は年末年始を除く。破砕、粗大ごみの搬入受付は16:00まで。"}},{"type":"Feature","geometry":{"type":"Point","coordinates":[134.07846,34.35143]},"properties":{"#property":"3","name":"高松市衛生センター","address":"高松市朝日町五丁目5-56","telephoneNumber":"087-821-0428","referenceObject":"http://www.city.takamatsu.kagawa.jp/kurashi/shinotorikumi/soshikihyo/eisei.html","note":"","availableDate":"月火水木金","startTime":"08:00","endTime":"16:00","availableDateNote":"利用可能曜日は祝祭日除く。し尿等収集運搬許可業者のみ搬入可"}},{"type":"Feature","geometry":{"type":"Point","coordinates":[134.07206,34.33889]},"properties":{"#property":"4","name":"高松市環境業務センター","address":"高松市木太町2282-1","telephoneNumber":"（環境業務課）087-834-0389、087-861-4524（環境指導課）087-839-2380（適正処理対策室）087-839-2370","referenceObject":"（環境業務課）http://www.city.takamatsu.kagawa.jp/kurashi/shinotorikumi/soshikihyo/kankyogyomu.html（環境指導課）http://www.city.takamatsu.kagawa.jp/kurashi/shinotorikumi/soshikihyo/kankyoshido.html（適正処理対策室）http://www.city.takamatsu.kagawa.jp/kurashi/shinotorikumi/soshikihyo/tekiseisyoritaisaku.html","note":"","availableDate":"月火水木金","startTime":"08:00","endTime":"16:45","availableDateNote":"利用可能曜日は祝祭日及び年末年始を除く。"}}]}