{"type":"FeatureCollection","features":[{"type":"Feature","geometry":{"type":"Point","coordinates":[134.07344944,34.34079917]},"properties":{"#property":"1","name":"高松市斎場公園","address":"高松市福岡町四丁目35-41","telephoneNumber":"087-822-1917","referenceObject":"http://www.city.takamatsu.kagawa.jp/kurashi/kurashi/bochi/sougi/park2.html","note":"","availableDate":"月火水木金土日","startTime":"08:30","endTime":"17:00","availableDateNote":"1月1日及び友引は休場日。"}},{"type":"Feature","geometry":{"type":"Point","coordinates":[134.14479639,34.32155833]},"properties":{"#property":"2","name":"高松市牟礼斎場","address":"高松市牟礼町原2260-2","telephoneNumber":"087-845-4944","referenceObject":"http://www.city.takamatsu.kagawa.jp/kurashi/kurashi/bochi/sougi/mure.html","note":"","availableDate":"月火水木金土日","startTime":"08:30","endTime":"17:00","availableDateNote":"1月1日及び友引は休場日。"}},{"type":"Feature","geometry":{"type":"Point","coordinates":[134.13615889,34.39073917]},"properties":{"#property":"3","name":"高松市庵治斎場","address":"高松市庵治町1391-1","telephoneNumber":"087-871-2539","referenceObject":"http://www.city.takamatsu.kagawa.jp/kurashi/kurashi/bochi/sougi/aji.html","note":"","availableDate":"月火水木金土日","startTime":"08:30","endTime":"17:00","availableDateNote":"1月1日及び友引は休場日。"}},{"type":"Feature","geometry":{"type":"Point","coordinates":[134.05234111,34.2237425]},"properties":{"#property":"4","name":"高松市やすらぎ苑","address":"高松市香川町川内原2200","telephoneNumber":"087-879-1222","referenceObject":"http://www.city.takamatsu.kagawa.jp/kurashi/kurashi/bochi/sougi/yasuragien.html","note":"","availableDate":"月火水木金土日","startTime":"08:30","endTime":"17:00","availableDateNote":"1月1日及び友引は休場日。"}}]}